poe_client/__init__.py
poe_client/client/__init__.py
poe_client/client/client.py
poe_client/client/poe_client.py
poe_client/schema/__init__.py
poe_client/schema/client_schema.py
poe_client/schema/schema.py
poe_async_client-0.0.6.dist-info/LICENSE
poe_async_client-0.0.6.dist-info/METADATA
poe_async_client-0.0.6.dist-info/WHEEL
poe_async_client-0.0.6.dist-info/top_level.txt
poe_async_client-0.0.6.dist-info/RECORD
